MGFEA/ModelPlot.py
MGFEA/__init__.py
MGFEA/model.py
MGFEA/multiGraphFEA.py
MGFEA/preprocess.py
MGFEA/train.py
MGFEA-1.0.0.dist-info/LICENSE
MGFEA-1.0.0.dist-info/METADATA
MGFEA-1.0.0.dist-info/WHEEL
MGFEA-1.0.0.dist-info/top_level.txt
MGFEA-1.0.0.dist-info/RECORD
