Metadata-Version: 2.1
Name: MGFEA
Version: 1.0.0
Summary: A package for single cell flux prediction
Home-page: https://github.com/Sunwenzhilab/MGFEA/
Author: luojiaxu
Author-email: 925009185@qq.com
License: MIT Licence
Keywords: pip,MGFEA
Classifier: Programming Language :: Python :: 3.7
Classifier: License :: OSI Approved :: MIT License
Classifier: Operating System :: POSIX :: Linux
License-File: LICENSE
Requires-Dist: torch
Requires-Dist: scipy
Requires-Dist: scanpy
Requires-Dist: torch-geometric
